{
  "R12": {
    "coefficients_ascending": [
      "4096",
      "-12288",
      "24576",
      "-20480",
      "135",
      "36702",
      "-49071",
      "36837",
      "0",
      "-20480",
      "24576",
      "-12288",
      "4096"
    ],
    "degree": 12,
    "full_sequence_artifact": "sturm_sequences_full.json.gz",
    "interval_variation_certificates": [],
    "positive_isolating_intervals": [],
    "positive_root_count": 0,
    "signs_at_positive_infinity": [
      1,
      1,
      -1,
      -1,
      1,
      1,
      1,
      -1,
      1,
      -1,
      -1,
      -1,
      1
    ],
    "signs_at_zero": [
      1,
      -1,
      -1,
      -1,
      1,
      -1,
      -1,
      -1,
      1,
      1,
      -1,
      1,
      1
    ],
    "sturm_sequence_length": 13,
    "sturm_sequence_sha256": "886269565d2a5ed66a0eb4cf3e2d0b699f0d44d7cc73848f4fd6bb2bb09db30a",
    "variations_at_positive_infinity": 6,
    "variations_at_zero": 6
  },
  "R35": {
    "coefficients_ascending": [
      "-62224",
      "186672",
      "456096",
      "-1555280",
      "-1865760",
      "5805504",
      "6692888",
      "-13234536",
      "-17525520",
      "19051760",
      "1044252504",
      "-3073330992",
      "-688686641",
      "8927316075",
      "-3527634150",
      "-8677213507",
      "3507151656",
      "5380558488",
      "244237845",
      "-8281660935",
      "4204399616",
      "7950200832",
      "-10038718464",
      "633210880",
      "6163752960",
      "-5056665600",
      "72058880",
      "2242652160",
      "-1415577600",
      "131072000",
      "415236096",
      "-223346688",
      "48234496",
      "31457280",
      "-15728640",
      "5242880"
    ],
    "degree": 35,
    "full_sequence_artifact": "sturm_sequences_full.json.gz",
    "interval_variation_certificates": [
      {
        "interval": [
          "3811056996847241979222071854257306818054/11127713288444321136063804263957304540649",
          "5596943962656029771075113763059930238743/16342234650242394728778816036158295288189"
        ],
        "left_signs": [
          -1,
          1,
          1,
          1,
          -1,
          -1,
          1,
          -1,
          -1,
          -1,
          1,
          -1,
          -1,
          1,
          1,
          -1,
          -1,
          1,
          1,
          -1,
          -1,
          1,
          1,
          -1,
          -1,
          -1,
          1,
          1,
          -1,
          1,
          -1,
          1,
          1,
          1,
          1,
          -1
        ],
        "left_variations": 18,
        "right_signs": [
          1,
          1,
          1,
          1,
          -1,
          -1,
          1,
          -1,
          -1,
          -1,
          1,
          -1,
          -1,
          1,
          1,
          -1,
          -1,
          1,
          1,
          -1,
          -1,
          1,
          1,
          -1,
          -1,
          -1,
          1,
          1,
          -1,
          1,
          -1,
          1,
          1,
          1,
          1,
          -1
        ],
        "right_variations": 17,
        "root_count": 1
      },
      {
        "interval": [
          "26056201297246505028899151752486212772904/28057145806712656217091798993740223934253",
          "17983421603059138519336082711370422249117/19364429843959501590177849731745817726775"
        ],
        "left_signs": [
          1,
          -1,
          -1,
          -1,
          1,
          1,
          -1,
          -1,
          -1,
          1,
          1,
          -1,
          -1,
          1,
          1,
          -1,
          -1,
          1,
          1,
          -1,
          -1,
          1,
          1,
          -1,
          1,
          1,
          1,
          -1,
          -1,
          1,
          1,
          -1,
          1,
          1,
          -1,
          -1
        ],
        "left_variations": 17,
        "right_signs": [
          -1,
          -1,
          -1,
          -1,
          1,
          1,
          -1,
          -1,
          -1,
          1,
          1,
          -1,
          -1,
          1,
          1,
          -1,
          -1,
          1,
          1,
          -1,
          -1,
          1,
          1,
          -1,
          1,
          1,
          1,
          -1,
          -1,
          1,
          1,
          -1,
          1,
          1,
          -1,
          -1
        ],
        "right_variations": 16,
        "root_count": 1
      },
      {
        "interval": [
          "33648180411229546381241690950706607083288/33775476676971230004379184491716619186483",
          "30811066493705016547377709292463931555475/30927629519111834924631833362376157425123"
        ],
        "left_signs": [
          -1,
          1,
          1,
          1,
          -1,
          -1,
          1,
          1,
          1,
          -1,
          -1,
          1,
          1,
          -1,
          -1,
          1,
          1,
          1,
          -1,
          1,
          1,
          -1,
          -1,
          -1,
          1,
          1,
          -1,
          -1,
          -1,
          1,
          1,
          -1,
          1,
          1,
          -1,
          -1
        ],
        "left_variations": 16,
        "right_signs": [
          1,
          1,
          1,
          1,
          -1,
          -1,
          1,
          1,
          1,
          -1,
          -1,
          1,
          1,
          -1,
          -1,
          1,
          1,
          1,
          -1,
          1,
          1,
          -1,
          -1,
          -1,
          1,
          1,
          -1,
          -1,
          -1,
          1,
          1,
          -1,
          1,
          1,
          -1,
          -1
        ],
        "right_variations": 15,
        "root_count": 1
      }
    ],
    "positive_isolating_intervals": [
      [
        "3811056996847241979222071854257306818054/11127713288444321136063804263957304540649",
        "5596943962656029771075113763059930238743/16342234650242394728778816036158295288189"
      ],
      [
        "26056201297246505028899151752486212772904/28057145806712656217091798993740223934253",
        "17983421603059138519336082711370422249117/19364429843959501590177849731745817726775"
      ],
      [
        "33648180411229546381241690950706607083288/33775476676971230004379184491716619186483",
        "30811066493705016547377709292463931555475/30927629519111834924631833362376157425123"
      ]
    ],
    "positive_root_count": 3,
    "signs_at_positive_infinity": [
      1,
      1,
      -1,
      -1,
      -1,
      -1,
      1,
      1,
      -1,
      -1,
      -1,
      1,
      -1,
      -1,
      -1,
      1,
      1,
      1,
      -1,
      -1,
      1,
      -1,
      -1,
      1,
      1,
      1,
      -1,
      -1,
      -1,
      1,
      1,
      -1,
      1,
      1,
      -1,
      -1
    ],
    "signs_at_zero": [
      -1,
      1,
      1,
      1,
      -1,
      -1,
      1,
      -1,
      -1,
      -1,
      1,
      -1,
      -1,
      1,
      1,
      -1,
      -1,
      1,
      1,
      -1,
      -1,
      1,
      1,
      -1,
      -1,
      1,
      1,
      1,
      -1,
      1,
      -1,
      1,
      1,
      1,
      1,
      -1
    ],
    "sturm_sequence_length": 36,
    "sturm_sequence_sha256": "8e54dc381cf03361b7ce557442c9316d4301e27a484af827454f43ad4d6c4af7",
    "variations_at_positive_infinity": 15,
    "variations_at_zero": 18
  },
  "diagonal": {
    "coefficients_ascending": [
      "-1",
      "0",
      "0",
      "-5",
      "0",
      "3",
      "0",
      "0",
      "0",
      "0",
      "16384",
      "0",
      "0",
      "20480"
    ],
    "degree": 13,
    "full_sequence_artifact": "sturm_sequences_full.json.gz",
    "interval_variation_certificates": [
      {
        "interval": [
          "7255729705021745707328703605448554939068/18839720052074373922731749580086837798587",
          "7975245987688687794893155132322267308535/20707965685449132583240665011791162458133"
        ],
        "left_signs": [
          -1,
          1,
          1,
          -1,
          -1,
          1,
          1,
          -1,
          -1,
          1,
          1,
          1,
          -1
        ],
        "left_variations": 6,
        "right_signs": [
          1,
          1,
          1,
          -1,
          -1,
          1,
          1,
          -1,
          -1,
          1,
          1,
          1,
          -1
        ],
        "right_variations": 5,
        "root_count": 1
      }
    ],
    "positive_isolating_intervals": [
      [
        "7255729705021745707328703605448554939068/18839720052074373922731749580086837798587",
        "7975245987688687794893155132322267308535/20707965685449132583240665011791162458133"
      ]
    ],
    "positive_root_count": 1,
    "signs_at_positive_infinity": [
      1,
      1,
      -1,
      -1,
      1,
      1,
      1,
      1,
      -1,
      1,
      1,
      1,
      -1
    ],
    "signs_at_zero": [
      -1,
      0,
      1,
      0,
      -1,
      0,
      1,
      -1,
      -1,
      1,
      1,
      -1,
      -1
    ],
    "sturm_sequence_length": 13,
    "sturm_sequence_sha256": "f2291a162c2629d710960beac7a00961953ef32ef30c24449027f5807bd2d555",
    "variations_at_positive_infinity": 5,
    "variations_at_zero": 6
  },
  "epsilon": "1/100000000000000000000000000000000000000000000000000000000000000000000000000000000"
}
